pytest_girder/__init__.py
pytest_girder/assertions.py
pytest_girder/fixtures.py
pytest_girder/plugin.py
pytest_girder/plugin_registry.py
pytest_girder/utils.py
pytest_girder/web_client.py
pytest_girder-5.0.0a14.dev27.dist-info/licenses/LICENSE
pytest_girder-5.0.0a14.dev27.dist-info/METADATA
pytest_girder-5.0.0a14.dev27.dist-info/WHEEL
pytest_girder-5.0.0a14.dev27.dist-info/entry_points.txt
pytest_girder-5.0.0a14.dev27.dist-info/top_level.txt
pytest_girder-5.0.0a14.dev27.dist-info/RECORD
