Metadata-Version: 2.4
Name: pytest-girder
Version: 5.0.0a14.dev27
Summary: A set of pytest fixtures for testing Girder applications.
Author: Kitware, Inc.
Author-email: kitware@kitware.com
License: Apache 2.0
Classifier: Framework :: Pytest
Requires-Python: >=3.10
License-File: LICENSE
Requires-Dist: girder>=3
Requires-Dist: mongomock
Requires-Dist: pytest>=3.6
Requires-Dist: pytest-cov
Requires-Dist: pymongo
Dynamic: author
Dynamic: author-email
Dynamic: classifier
Dynamic: license
Dynamic: license-file
Dynamic: requires-dist
Dynamic: requires-python
Dynamic: summary
